api_watchdog/__init__.py
api_watchdog/cli.py
api_watchdog/collect.py
api_watchdog/core.py
api_watchdog/result_error.py
api_watchdog/runner.py
api_watchdog/validate.py
api_watchdog/formatters/__init__.py
api_watchdog/formatters/result_group_html.py
api_watchdog/hooks/__init__.py
api_watchdog/hooks/result_group/__init__.py
api_watchdog/hooks/result_group/abstract.py
api_watchdog/hooks/result_group/mailgun.py
api_watchdog/integrations/__init__.py
api_watchdog/integrations/trapi.py
api_watchdog/mixins/__init__.py
api_watchdog/mixins/mailgun.py
api_watchdog-0.6.0.dist-info/LICENSE
api_watchdog-0.6.0.dist-info/METADATA
api_watchdog-0.6.0.dist-info/WHEEL
api_watchdog-0.6.0.dist-info/entry_points.txt
api_watchdog-0.6.0.dist-info/top_level.txt
api_watchdog-0.6.0.dist-info/RECORD
