Metadata-Version: 2.1
Name: api-watchdog
Version: 0.6.0
Summary: API watchdog
Home-page: UNKNOWN
License: MIT
Platform: UNKNOWN
License-File: LICENSE
Requires-Dist: pydantic (>=1.8.2)
Requires-Dist: jq (>=1.2.1)
Requires-Dist: requests (>=2.26.0)
Provides-Extra: trapi
Requires-Dist: reasoner-pydantic ; extra == 'trapi'
